[
  {
    "term": "ecstatic",
    "ipa": "/ekˈstætɪk/",
    "target_translation": "vô cùng hạnh phúc / ngây ngất",
    "source_translation": "feeling or expressing overwhelming happiness or joyful excitement",
    "example": "She was ecstatic when she found out she had been accepted into her dream university.",
    "pos": "adjective",
    "source_lang": "en",
    "target_lang": "vi",
    "popular_score": 88,
    "difficulty": 5,
    "collocations": ["absolutely ecstatic", "ecstatic fans"],
    "synonyms": ["joyful", "elated", "overjoyed"],
    "topics": ["emotions", "happiness"],
    "skills": ["speaking", "writing"]
  },
  {
    "term": "melancholy",
    "ipa": "/ˈmelənkəli/",
    "target_translation": "u sầu / u uất",
    "source_translation": "a feeling of pensive sadness, typically with no obvious cause",
    "example": "The rainy weather always puts him in a melancholy mood.",
    "pos": "noun/adjective",
    "source_lang": "en",
    "target_lang": "vi",
    "popular_score": 82,
    "difficulty": 7,
    "collocations": ["a sense of melancholy", "deep melancholy"],
    "synonyms": ["sadness", "sorrow", "despondency"],
    "topics": ["emotions", "sadness"],
    "skills": ["reading", "writing"]
  },
  {
    "term": "frustrated",
    "ipa": "/ˈfrʌstreɪtɪd/",
    "target_translation": "bực bội / nản lòng",
    "source_translation": "feeling annoyed or less confident because you cannot achieve what you want",
    "example": "I feel very frustrated when my computer keeps freezing while I'm working.",
    "pos": "adjective",
    "source_lang": "en",
    "target_lang": "vi",
    "popular_score": 95,
    "difficulty": 4,
    "collocations": ["get frustrated", "frustrated with"],
    "synonyms": ["annoyed", "exasperated"],
    "topics": ["emotions", "negative_feelings"],
    "skills": ["speaking", "listening"]
  },
  {
    "term": "ambivalent",
    "ipa": "/æmˈbɪvələnt/",
    "target_translation": "mâu thuẫn / vừa yêu vừa ghét",
    "source_translation": "having mixed feelings or contradictory ideas about something or someone",
    "example": "He has an ambivalent attitude toward his job; he likes the salary but hates the commute.",
    "pos": "adjective",
    "source_lang": "en",
    "target_lang": "vi",
    "popular_score": 75,
    "difficulty": 8,
    "collocations": ["feel ambivalent about"],
    "synonyms": ["uncertain", "equivocal"],
    "topics": ["emotions", "complexity"],
    "skills": ["reading", "writing"]
  },
  {
    "term": "content",
    "ipa": "/kənˈtent/",
    "target_translation": "hài lòng / mãn nguyện",
    "source_translation": "in a state of peaceful happiness and satisfaction",
    "example": "After a long day of work, sitting by the fireplace made her feel perfectly content.",
    "pos": "adjective",
    "source_lang": "en",
    "target_lang": "vi",
    "popular_score": 90,
    "difficulty": 4,
    "collocations": ["perfectly content", "content with"],
    "synonyms": ["satisfied", "pleased"],
    "topics": ["emotions", "happiness"],
    "skills": ["speaking", "reading"]
  },
  {
    "term": "overwhelmed",
    "ipa": "/ˌəʊvərˈwelmd/",
    "target_translation": "choáng ngợp / quá tải",
    "source_translation": "feeling a sudden strong emotion or having too much to deal with",
    "example": "The staff were overwhelmed by the number of complaints they received.",
    "pos": "adjective",
    "source_lang": "en",
    "target_lang": "vi",
    "popular_score": 94,
    "difficulty": 5,
    "collocations": ["completely overwhelmed", "overwhelmed with joy"],
    "synonyms": ["overloaded", "swamped"],
    "topics": ["emotions", "stress"],
    "skills": ["speaking", "listening"]
  },
  {
    "term": "apprehensive",
    "ipa": "/ˌæprɪˈhensɪv/",
    "target_translation": "lo lắng / e sợ",
    "source_translation": "anxious or fearful that something bad or unpleasant will happen",
    "example": "I'm a bit apprehensive about the surgery tomorrow.",
    "pos": "adjective",
    "source_lang": "en",
    "target_lang": "vi",
    "popular_score": 78,
    "difficulty": 7,
    "collocations": ["feel apprehensive", "apprehensive about"],
    "synonyms": ["anxious", "worried", "uneasy"],
    "topics": ["emotions", "fear"],
    "skills": ["reading", "writing"]
  },
  {
    "term": "nostalgic",
    "ipa": "/nəˈstældʒɪk/",
    "target_translation": "hoài niệm",
    "source_translation": "feeling a sentimental longing or wistful affection for the past",
    "example": "Looking at old family photos makes me feel very nostalgic.",
    "pos": "adjective",
    "source_lang": "en",
    "target_lang": "vi",
    "popular_score": 91,
    "difficulty": 5,
    "collocations": ["feel nostalgic", "nostalgic for"],
    "synonyms": ["wistful", "sentimental"],
    "topics": ["emotions", "memory"],
    "skills": ["speaking", "listening"]
  },
  {
    "term": "indignant",
    "ipa": "/ɪnˈdɪɡnənt/",
    "target_translation": "phẫn nộ (vì thấy bất công)",
    "source_translation": "feeling or showing anger or annoyance at what is perceived as unfair treatment",
    "example": "He was indignant at the suggestion that he had cheated.",
    "pos": "adjective",
    "source_lang": "en",
    "target_lang": "vi",
    "popular_score": 72,
    "difficulty": 8,
    "collocations": ["become indignant", "indignant tone"],
    "synonyms": ["resentful", "aggrieved"],
    "topics": ["emotions", "anger"],
    "skills": ["reading", "writing"]
  },
  {
    "term": "empathetic",
    "ipa": "/ˌempəˈθetɪk/",
    "target_translation": "thấu cảm",
    "source_translation": "showing an ability to understand and share the feelings of another",
    "example": "A good therapist must be empathetic and non-judgmental.",
    "pos": "adjective",
    "source_lang": "en",
    "target_lang": "vi",
    "popular_score": 89,
    "difficulty": 6,
    "collocations": ["empathetic listener", "highly empathetic"],
    "synonyms": ["compassionate", "understanding"],
    "topics": ["emotions", "social_skills"],
    "skills": ["speaking", "writing"]
  },
  {
    "term": "on cloud nine",
    "ipa": "/ɒn klaʊd naɪn/",
    "target_translation": "vô cùng hạnh phúc / lên tận tầng mây",
    "source_translation": "to be extremely happy and excited",
    "example": "He's been on cloud nine ever since he got the promotion.",
    "pos": "idiom",
    "source_lang": "en",
    "target_lang": "vi",
    "popular_score": 92,
    "difficulty": 4,
    "collocations": ["be on cloud nine", "feel like on cloud nine"],
    "synonyms": ["overjoyed", "blissful"],
    "topics": ["emotions", "happiness"],
    "skills": ["speaking", "listening"]
  },
  {
    "term": "down in the dumps",
    "ipa": "/daʊn ɪn ðə dʌmps/",
    "target_translation": "buồn bã / chán nản",
    "source_translation": "feeling unhappy or without much hope",
    "example": "She’s been a bit down in the dumps since her best friend moved away.",
    "pos": "idiom",
    "source_lang": "en",
    "target_lang": "vi",
    "popular_score": 85,
    "difficulty": 5,
    "collocations": ["feel down in the dumps"],
    "synonyms": ["depressed", "miserable"],
    "topics": ["emotions", "sadness"],
    "skills": ["speaking", "listening"]
  },
  {
    "term": "mixed emotions",
    "ipa": "/mɪkst ɪˈməʊʃnz/",
    "target_translation": "cảm xúc hỗn độn",
    "source_translation": "having both positive and negative feelings about something at the same time",
    "example": "I have mixed emotions about moving; I'm excited for the new job but sad to leave my family.",
    "pos": "noun phrase",
    "source_lang": "en",
    "target_lang": "vi",
    "popular_score": 94,
    "difficulty": 3,
    "collocations": ["have mixed emotions about"],
    "synonyms": ["ambivalence"],
    "topics": ["emotions", "complexity"],
    "skills": ["speaking", "writing"]
  },
  {
    "term": "bottle up",
    "ipa": "/ˈbɒtl ʌp/",
    "target_translation": "kìm nén cảm xúc",
    "source_translation": "to deliberately not allow yourself to show or talk about your feelings",
    "example": "It’s not healthy to bottle up your anger; you should talk to someone.",
    "pos": "phrasal verb",
    "source_lang": "en",
    "target_lang": "vi",
    "popular_score": 88,
    "difficulty": 5,
    "collocations": ["bottle up emotions", "bottle up feelings"],
    "synonyms": ["suppress", "repress"],
    "topics": ["emotions", "mental_health"],
    "skills": ["speaking", "listening"]
  },
  {
    "term": "exasperated",
    "ipa": "/ɪɡˈzæspəreɪtɪd/",
    "target_translation": "bực đến phát điên / hết kiên nhẫn",
    "source_translation": "intensely irritated and frustrated",
    "example": "The teacher gave an exasperated sigh when the students refused to listen.",
    "pos": "adjective",
    "source_lang": "en",
    "target_lang": "vi",
    "popular_score": 79,
    "difficulty": 7,
    "collocations": ["exasperated by", "exasperated tone"],
    "synonyms": ["infuriated", "annoyed"],
    "topics": ["emotions", "anger"],
    "skills": ["reading", "writing"]
  },
  {
    "term": "vulnerable",
    "ipa": "/ˈvʌlnərəbl/",
    "target_translation": "dễ bị tổn thương",
    "source_translation": "feeling unprotected and exposed to the possibility of being attacked or harmed, either physically or emotionally",
    "example": "Sharing your personal story makes you feel vulnerable, but it builds trust.",
    "pos": "adjective",
    "source_lang": "en",
    "target_lang": "vi",
    "popular_score": 90,
    "difficulty": 6,
    "collocations": ["feel vulnerable", "emotionally vulnerable"],
    "synonyms": ["exposed", "sensitive"],
    "topics": ["emotions", "psychology"],
    "skills": ["speaking", "reading"]
  },
  {
    "term": "lose one's cool",
    "ipa": "/luːz wʌnz kuːl/",
    "target_translation": "mất bình tĩnh / nổi nóng",
    "source_translation": "to suddenly become very angry or upset and stop being calm",
    "example": "I’m usually a patient person, but I really lost my cool when he lied to me.",
    "pos": "idiom",
    "source_lang": "en",
    "target_lang": "vi",
    "popular_score": 93,
    "difficulty": 4,
    "collocations": ["almost lose one's cool"],
    "synonyms": ["blow a fuse", "lose one's temper"],
    "topics": ["emotions", "anger"],
    "skills": ["speaking", "listening"]
  },
  {
    "term": "resilient",
    "ipa": "/rɪˈzɪliənt/",
    "target_translation": "kiên cường / mau phục hồi",
    "source_translation": "able to withstand or recover quickly from difficult conditions",
    "example": "Children are often more resilient than we give them credit for.",
    "pos": "adjective",
    "source_lang": "en",
    "target_lang": "vi",
    "popular_score": 86,
    "difficulty": 7,
    "collocations": ["resilient nature", "stay resilient"],
    "synonyms": ["tough", "strong"],
    "topics": ["emotions", "personality"],
    "skills": ["reading", "writing"]
  },
  {
    "term": "burst with joy",
    "ipa": "/bɜːrst wɪð dʒɔɪ/",
    "target_translation": "tràn ngập niềm vui",
    "source_translation": "to have a very strong feeling of happiness",
    "example": "They were bursting with joy when their first grandchild was born.",
    "pos": "verb phrase",
    "source_lang": "en",
    "target_lang": "vi",
    "popular_score": 82,
    "difficulty": 4,
    "collocations": ["bursting with pride"],
    "synonyms": ["elated"],
    "topics": ["emotions", "happiness"],
    "skills": ["speaking", "listening"]
  },
  {
    "term": "appalled",
    "ipa": "/əˈpɔːld/",
    "target_translation": "kinh hãi / kinh tởm",
    "source_translation": "greatly dismayed or horrified",
    "example": "I was appalled by the lack of hygiene in the restaurant kitchen.",
    "pos": "adjective",
    "source_lang": "en",
    "target_lang": "vi",
    "popular_score": 77,
    "difficulty": 6,
    "collocations": ["absolutely appalled", "appalled by the news"],
    "synonyms": ["horrified", "shocked"],
    "topics": ["emotions", "negative_feelings"],
    "skills": ["reading", "listening"]
  },
  {
    "term": "resentful",
    "ipa": "/rɪˈzentfl/",
    "target_translation": "uất ức / oán giận",
    "source_translation": "feeling or expressing bitterness or indignation at having been treated unfairly",
    "example": "He felt deeply resentful that his younger brother inherited the entire estate.",
    "pos": "adjective",
    "source_lang": "en",
    "target_lang": "vi",
    "popular_score": 84,
    "difficulty": 6,
    "collocations": ["feel resentful toward", "grow resentful"],
    "synonyms": ["bitter", "aggrieved"],
    "topics": ["emotions", "social_life"],
    "skills": ["reading", "writing"]
  },
  {
    "term": "green with envy",
    "ipa": "/ɡriːn wɪð ˈenvi/",
    "target_translation": "ghen tị đến nổ mắt",
    "source_translation": "extremely jealous of someone else's possessions or success",
    "example": "When she saw my new car, she was absolutely green with envy.",
    "pos": "idiom",
    "source_lang": "en",
    "target_lang": "vi",
    "popular_score": 88,
    "difficulty": 5,
    "collocations": ["be green with envy", "make someone green with envy"],
    "synonyms": ["jealous", "envious"],
    "topics": ["emotions", "social_life"],
    "skills": ["speaking", "listening"]
  },
  {
    "term": "guilt-ridden",
    "ipa": "/ˈɡɪlt rɪdn/",
    "target_translation": "bị giày vò bởi tội lỗi",
    "source_translation": "filled with a sense of guilt",
    "example": "She felt guilt-ridden after forgetting her mother's birthday for the second year in a row.",
    "pos": "adjective",
    "source_lang": "en",
    "target_lang": "vi",
    "popular_score": 76,
    "difficulty": 7,
    "collocations": ["guilt-ridden conscience", "guilt-ridden expression"],
    "synonyms": ["remorseful", "ashamed"],
    "topics": ["emotions", "psychology"],
    "skills": ["reading", "writing"]
  },
  {
    "term": "self-conscious",
    "ipa": "/ˌself ˈkɑːnʃəs/",
    "target_translation": "tự ti / e dè (vì lo người khác nhìn mình)",
    "source_translation": "feeling undue awareness of oneself, one's appearance, or one's actions",
    "example": "I felt very self-conscious walking into the party wearing casual clothes while everyone else was in formal wear.",
    "pos": "adjective",
    "source_lang": "en",
    "target_lang": "vi",
    "popular_score": 91,
    "difficulty": 5,
    "collocations": ["feel self-conscious", "highly self-conscious"],
    "synonyms": ["embarrassed", "awkward"],
    "topics": ["emotions", "personality"],
    "skills": ["speaking", "listening"]
  },
  {
    "term": "make someone's blood boil",
    "ipa": "/meɪk ˈsʌmwʌnz blʌd bɔɪl/",
    "target_translation": "làm ai đó sôi máu / cực kỳ tức giận",
    "source_translation": "to cause someone to become extremely angry",
    "example": "The way they treat their animals just makes my blood boil.",
    "pos": "idiom",
    "source_lang": "en",
    "target_lang": "vi",
    "popular_score": 85,
    "difficulty": 6,
    "collocations": [],
    "synonyms": ["infuriate", "enrage"],
    "topics": ["emotions", "anger"],
    "skills": ["speaking", "listening"]
  },
  {
    "term": "lonely",
    "ipa": "/ˈləʊnli/",
    "target_translation": "cô đơn",
    "source_translation": "sad because one has no friends or company",
    "example": "Moving to a new city can be very lonely at first.",
    "pos": "adjective",
    "source_lang": "en",
    "target_lang": "vi",
    "popular_score": 99,
    "difficulty": 2,
    "collocations": ["feel lonely", "lonely heart"],
    "synonyms": ["solitary", "isolated"],
    "topics": ["emotions", "social_life"],
    "skills": ["speaking", "listening"]
  },
  {
    "term": "over the moon",
    "ipa": "/ˈəʊvər ðə muːn/",
    "target_translation": "vô cùng sung sướng / sướng rơn",
    "source_translation": "extremely happy or delighted",
    "example": "They were over the moon when they won the lottery.",
    "pos": "idiom",
    "source_lang": "en",
    "target_lang": "vi",
    "popular_score": 94,
    "difficulty": 4,
    "collocations": ["be over the moon"],
    "synonyms": ["ecstatic", "thrilled"],
    "topics": ["emotions", "happiness"],
    "skills": ["speaking", "listening"]
  },
  {
    "term": "indifferent",
    "ipa": "/ɪnˈdɪfrənt/",
    "target_translation": "thờ ơ / hờ hững",
    "source_translation": "having no particular interest or sympathy; unconcerned",
    "example": "He was strangely indifferent to the news of his own promotion.",
    "pos": "adjective",
    "source_lang": "en",
    "target_lang": "vi",
    "popular_score": 82,
    "difficulty": 6,
    "collocations": ["remain indifferent", "indifferent to"],
    "synonyms": ["apathetic", "uninterested"],
    "topics": ["emotions", "complexity"],
    "skills": ["reading", "writing"]
  },
  {
    "term": "a weight off one's shoulders",
    "ipa": "/ə weɪt ɔːf wʌnz ˈʃəʊldərz/",
    "target_translation": "trút bỏ được gánh nặng",
    "source_translation": "a feeling of relief from a burden or worry",
    "example": "Finally telling her the truth was a huge weight off my shoulders.",
    "pos": "idiom",
    "source_lang": "en",
    "target_lang": "vi",
    "popular_score": 89,
    "difficulty": 5,
    "collocations": ["feel like a weight off my shoulders"],
    "synonyms": ["relief"],
    "topics": ["emotions", "relief"],
    "skills": ["speaking", "listening"]
  },
  {
    "term": "scared stiff",
    "ipa": "/skerd stɪf/",
    "target_translation": "sợ cứng người / sợ chết khiếp",
    "source_translation": "extremely frightened to the point where you cannot move",
    "example": "I'm scared stiff of heights, so I won't go up the Eiffel Tower.",
    "pos": "idiom",
    "source_lang": "en",
    "target_lang": "vi",
    "popular_score": 81,
    "difficulty": 4,
    "collocations": ["be scared stiff"],
    "synonyms": ["terrified", "petrified"],
    "topics": ["emotions", "fear"],
    "skills": ["speaking", "listening"]
  },
  {
    "term": "wear one's heart on one's sleeve",
    "ipa": "/wer wʌnz hɑːrt ɒn wʌnz sliːv/",
    "target_translation": "ruột để ngoài da / không giấu giếm cảm xúc",
    "source_translation": "to make your feelings and emotions obvious to other people",
    "example": "You always know how Sarah feels; she wears her heart on her sleeve.",
    "pos": "idiom",
    "source_lang": "en",
    "target_lang": "vi",
    "popular_score": 83,
    "difficulty": 6,
    "collocations": [],
    "synonyms": ["open", "candid"],
    "topics": ["emotions", "personality"],
    "skills": ["speaking", "writing"]
  },
  {
    "term": "devastated",
    "ipa": "/ˈdevəsteɪtɪd/",
    "target_translation": "tan nát / hoàn toàn sụp đổ",
    "source_translation": "extremely upset and shocked",
    "example": "The family was devastated by the sudden loss of their home in the fire.",
    "pos": "adjective",
    "source_lang": "en",
    "target_lang": "vi",
    "popular_score": 87,
    "difficulty": 5,
    "collocations": ["absolutely devastated", "devastated by the news"],
    "synonyms": ["shattered", "heartbroken"],
    "topics": ["emotions", "sadness"],
    "skills": ["speaking", "writing"]
  },
  {
    "term": "petrified",
    "ipa": "/ˈpetrɪfaɪd/",
    "target_translation": "sợ chết trân / sợ đến mức hóa đá",
    "source_translation": "so frightened that one is unable to move; terrified",
    "example": "I was petrified when I saw the snake slithering across the floor.",
    "pos": "adjective",
    "source_lang": "en",
    "target_lang": "vi",
    "popular_score": 88,
    "difficulty": 5,
    "collocations": ["absolutely petrified", "petrified of spiders"],
    "synonyms": ["terrified", "horror-stricken"],
    "topics": ["emotions", "fear"],
    "skills": ["speaking", "listening"]
  },
  {
    "term": "on pins and needles",
    "ipa": "/ɒn pɪnz ənd ˈniːdlz/",
    "target_translation": "bồn chồn / đứng ngồi không yên",
    "source_translation": "in a state of nervous anticipation or anxiety",
    "example": "We were on pins and needles waiting for the test results.",
    "pos": "idiom",
    "source_lang": "en",
    "target_lang": "vi",
    "popular_score": 82,
    "difficulty": 6,
    "collocations": ["be on pins and needles"],
    "synonyms": ["anxious", "nervous"],
    "topics": ["emotions", "anxiety"],
    "skills": ["speaking", "listening"]
  },
  {
    "term": "flabbergasted",
    "ipa": "/ˈflæbəɡæstɪd/",
    "target_translation": "sửng sốt / kinh ngạc tột độ",
    "source_translation": "greatly surprised or astonished",
    "example": "I was flabbergasted when he told me how much the house actually cost.",
    "pos": "adjective",
    "source_lang": "en",
    "target_lang": "vi",
    "popular_score": 75,
    "difficulty": 7,
    "collocations": ["left flabbergasted"],
    "synonyms": ["astounded", "amazed"],
    "topics": ["emotions", "surprise"],
    "skills": ["reading", "writing"]
  },
  {
    "term": "bewildered",
    "ipa": "/bɪˈwɪldərd/",
    "target_translation": "ngơ ngác / lúng túng / hoang mang",
    "source_translation": "confused and indecisive; puzzled",
    "example": "He looked bewildered by the complex instructions I gave him.",
    "pos": "adjective",
    "source_lang": "en",
    "target_lang": "vi",
    "popular_score": 84,
    "difficulty": 6,
    "collocations": ["completely bewildered", "bewildered expression"],
    "synonyms": ["confused", "baffled"],
    "topics": ["emotions", "confusion"],
    "skills": ["reading", "listening"]
  },
  {
    "term": "take someone by surprise",
    "ipa": "/teɪk ˈsʌmwʌn baɪ səˈpraɪz/",
    "target_translation": "làm ai đó bất ngờ / đánh úp",
    "source_translation": "to surprise someone by happening when they are not expecting it",
    "example": "The sudden heavy rain took us by surprise during our picnic.",
    "pos": "idiom",
    "source_lang": "en",
    "target_lang": "vi",
    "popular_score": 95,
    "difficulty": 3,
    "collocations": ["totally take me by surprise"],
    "synonyms": ["catch off guard"],
    "topics": ["emotions", "surprise"],
    "skills": ["speaking", "listening"]
  },
  {
    "term": "jittery",
    "ipa": "/ˈdʒɪtəri/",
    "target_translation": "bồn chồn / run rẩy (vì lo lắng)",
    "source_translation": "feeling nervous or uneasy, often accompanied by small physical movements",
    "example": "I always feel a bit jittery before giving a public speech.",
    "pos": "adjective",
    "source_lang": "en",
    "target_lang": "vi",
    "popular_score": 86,
    "difficulty": 5,
    "collocations": ["get jittery", "feel jittery"],
    "synonyms": ["nervous", "edgy"],
    "topics": ["emotions", "anxiety"],
    "skills": ["speaking", "listening"]
  },
  {
    "term": "dumbfounded",
    "ipa": "/ˌdʌmˈfaʊndɪd/",
    "target_translation": "chết lặng / không thốt nên lời",
    "source_translation": "so greatly astonished or amazed that one is unable to speak",
    "example": "The news of the scandal left the entire audience dumbfounded.",
    "pos": "adjective",
    "source_lang": "en",
    "target_lang": "vi",
    "popular_score": 79,
    "difficulty": 6,
    "collocations": ["utterly dumbfounded"],
    "synonyms": ["speechless", "stunned"],
    "topics": ["emotions", "surprise"],
    "skills": ["reading", "listening"]
  },
  {
    "term": "have a sinking feeling",
    "ipa": "/hæv ə ˈsɪŋkɪŋ ˈfiːlɪŋ/",
    "target_translation": "có linh cảm xấu",
    "source_translation": "a feeling that something bad is happening or will happen",
    "example": "I had a sinking feeling in my stomach when I saw the police car outside.",
    "pos": "idiom",
    "source_lang": "en",
    "target_lang": "vi",
    "popular_score": 89,
    "difficulty": 5,
    "collocations": ["get a sinking feeling"],
    "synonyms": ["dread", "premonition"],
    "topics": ["emotions", "fear"],
    "skills": ["speaking", "listening"]
  },
  {
    "term": "startled",
    "ipa": "/ˈstɑːrtld/",
    "target_translation": "giật mình / hốt hoảng",
    "source_translation": "feeling or showing sudden shock or alarm",
    "example": "A loud bang in the street startled me while I was sleeping.",
    "pos": "adjective",
    "source_lang": "en",
    "target_lang": "vi",
    "popular_score": 92,
    "difficulty": 4,
    "collocations": ["easily startled", "look startled"],
    "synonyms": ["surprised", "jumpy"],
    "topics": ["emotions", "surprise"],
    "skills": ["listening", "speaking"]
  },
  {
    "term": "on edge",
    "ipa": "/ɒn edʒ/",
    "target_translation": "căng thẳng / dễ nổi cáu",
    "source_translation": "tense, nervous, or irritable",
    "example": "Everyone at the office has been on edge since the announcement of the layoffs.",
    "pos": "idiom",
    "source_lang": "en",
    "target_lang": "vi",
    "popular_score": 90,
    "difficulty": 4,
    "collocations": ["be a bit on edge", "feel on edge"],
    "synonyms": ["tense", "anxious"],
    "topics": ["emotions", "stress"],
    "skills": ["speaking", "listening"]
  },
  {
    "term": "infuriated",
    "ipa": "/ɪnˈfjʊrieɪtɪd/",
    "target_translation": "cực kỳ giận dữ / phát tiết",
    "source_translation": "extremely angry and impatient",
    "example": "I was infuriated by the company's refusal to take responsibility for the error.",
    "pos": "adjective",
    "source_lang": "en",
    "target_lang": "vi",
    "popular_score": 88,
    "difficulty": 6,
    "collocations": ["absolutely infuriated", "infuriated by"],
    "synonyms": ["enraged", "incensed"],
    "topics": ["emotions", "anger"],
    "skills": ["speaking", "writing"]
  },
  {
    "term": "miserable",
    "ipa": "/ˈmɪzrəbl/",
    "target_translation": "khổ sở / tồi tệ",
    "source_translation": "very unhappy or uncomfortable",
    "example": "The cold, rainy weather made everyone feel miserable during the camping trip.",
    "pos": "adjective",
    "source_lang": "en",
    "target_lang": "vi",
    "popular_score": 95,
    "difficulty": 3,
    "collocations": ["feel miserable", "miserable failure"],
    "synonyms": ["unhappy", "wretched"],
    "topics": ["emotions", "sadness"],
    "skills": ["speaking", "listening"]
  },
  {
    "term": "see red",
    "ipa": "/siː red/",
    "target_translation": "giận đỏ mặt / mất kiểm soát vì giận",
    "source_translation": "to become very angry suddenly",
    "example": "When he saw the man hit the dog, he just saw red.",
    "pos": "idiom",
    "source_lang": "en",
    "target_lang": "vi",
    "popular_score": 84,
    "difficulty": 5,
    "collocations": ["make someone see red"],
    "synonyms": ["furious"],
    "topics": ["emotions", "anger"],
    "skills": ["speaking", "listening"]
  },
  {
    "term": "heartbroken",
    "ipa": "/ˈhɑːrtbrəʊkən/",
    "target_translation": "tan nát cõi lòng",
    "source_translation": "suffering from overwhelming distress; very upset",
    "example": "He was heartbroken when his cat passed away after fifteen years.",
    "pos": "adjective",
    "source_lang": "en",
    "target_lang": "vi",
    "popular_score": 97,
    "difficulty": 3,
    "collocations": ["absolutely heartbroken", "heartbroken by"],
    "synonyms": ["devastated", "grieved"],
    "topics": ["emotions", "sadness"],
    "skills": ["speaking", "writing"]
  },
  {
    "term": "at the end of one's tether",
    "ipa": "/æt ðə end əv wʌnz ˈteðər/",
    "target_translation": "kiệt sức / hết chịu nổi",
    "source_translation": "having no patience or energy left to cope with a difficult situation",
    "example": "With the baby crying and the house in a mess, she was at the end of her tether.",
    "pos": "idiom",
    "source_lang": "en",
    "target_lang": "vi",
    "popular_score": 76,
    "difficulty": 7,
    "collocations": ["be at the end of one's tether"],
    "synonyms": ["at the end of one's rope"],
    "topics": ["emotions", "stress"],
    "skills": ["speaking", "listening"]
  },
  {
    "term": "despondent",
    "ipa": "/dɪˈspɑːndənt/",
    "target_translation": "vô vọng / nản lòng",
    "source_translation": "in low spirits from loss of hope or courage",
    "example": "She grew despondent after her third job application was rejected.",
    "pos": "adjective",
    "source_lang": "en",
    "target_lang": "vi",
    "popular_score": 72,
    "difficulty": 8,
    "collocations": ["feel despondent", "increasingly despondent"],
    "synonyms": ["discouraged", "dejected"],
    "topics": ["emotions", "sadness"],
    "skills": ["reading", "writing"]
  },
  {
    "term": "blow one's top",
    "ipa": "/bləʊ wʌnz tɑːp/",
    "target_translation": "nổi trận lôi đình / giận dữ",
    "source_translation": "to lose one's temper and explode with anger",
    "example": "My dad blew his top when he saw the dent in his new car.",
    "pos": "idiom",
    "source_lang": "en",
    "target_lang": "vi",
    "popular_score": 83,
    "difficulty": 5,
    "collocations": [],
    "synonyms": ["hit the roof", "fly into a rage"],
    "topics": ["emotions", "anger"],
    "skills": ["speaking", "listening"]
  },
  {
    "term": "bittersweet",
    "ipa": "/ˌbɪtərˈswiːt/",
    "target_translation": "vừa ngọt ngào vừa cay đắng",
    "source_translation": "arousing pleasure tinged with sadness or pain",
    "example": "Graduation was a bittersweet moment; I was happy to finish but sad to leave my friends.",
    "pos": "adjective",
    "source_lang": "en",
    "target_lang": "vi",
    "popular_score": 91,
    "difficulty": 5,
    "collocations": ["bittersweet memory", "bittersweet ending"],
    "synonyms": [],
    "topics": ["emotions", "complexity"],
    "skills": ["speaking", "writing"]
  },
  {
    "term": "resentment",
    "ipa": "/rɪˈzentmənt/",
    "target_translation": "sự oán giận / hằn học",
    "source_translation": "bitter indignation at having been treated unfairly",
    "example": "She felt a flicker of resentment when her colleague got the credit for her idea.",
    "pos": "noun",
    "source_lang": "en",
    "target_lang": "vi",
    "popular_score": 85,
    "difficulty": 6,
    "collocations": ["harbor resentment", "feel resentment"],
    "synonyms": ["bitterness", "grudge"],
    "topics": ["emotions", "social_life"],
    "skills": ["reading", "writing"]
  },
  {
    "term": "livid",
    "ipa": "/ˈlɪvɪd/",
    "target_translation": "giận tím mặt",
    "source_translation": "furiously angry",
    "example": "He was absolutely livid when he found out they had lied to him.",
    "pos": "adjective",
    "source_lang": "en",
    "target_lang": "vi",
    "popular_score": 80,
    "difficulty": 6,
    "collocations": ["absolutely livid"],
    "synonyms": ["fuming", "outraged"],
    "topics": ["emotions", "anger"],
    "skills": ["speaking", "listening"]
  },
  {
    "term": "self-assured",
    "ipa": "/ˌself əˈʃʊrd/",
    "target_translation": "tự tin / quyết đoán",
    "source_translation": "confident in one's own abilities or character",
    "example": "She walked into the interview feeling self-assured and ready to answer any question.",
    "pos": "adjective",
    "source_lang": "en",
    "target_lang": "vi",
    "popular_score": 88,
    "difficulty": 6,
    "collocations": ["self-assured manner", "become more self-assured"],
    "synonyms": ["confident", "poised"],
    "topics": ["emotions", "personality"],
    "skills": ["speaking", "writing"]
  },
  {
    "term": "beaming with pride",
    "ipa": "/ˈbiːmɪŋ wɪð praɪd/",
    "target_translation": "rạng rỡ niềm tự hào",
    "source_translation": "to have a big smile because you are very proud of something",
    "example": "The parents were beaming with pride as their daughter received her diploma.",
    "pos": "idiom/verb phrase",
    "source_lang": "en",
    "target_lang": "vi",
    "popular_score": 90,
    "difficulty": 4,
    "collocations": [],
    "synonyms": ["glow with pride"],
    "topics": ["emotions", "happiness"],
    "skills": ["speaking", "listening"]
  },
  {
    "term": "optimistic",
    "ipa": "/ˌɑːptɪˈmɪstɪk/",
    "target_translation": "lạc quan",
    "source_translation": "hopeful and confident about the future or the success of something",
    "example": "Despite the setbacks, the team remains optimistic about winning the championship.",
    "pos": "adjective",
    "source_lang": "en",
    "target_lang": "vi",
    "popular_score": 96,
    "difficulty": 4,
    "collocations": ["cautiously optimistic", "highly optimistic"],
    "synonyms": ["hopeful", "positive"],
    "topics": ["emotions", "personality"],
    "skills": ["speaking", "reading"]
  },
  {
    "term": "empowered",
    "ipa": "/ɪmˈpaʊərd/",
    "target_translation": "được tiếp thêm sức mạnh / làm chủ bản thân",
    "source_translation": "feeling stronger and more confident, especially in controlling one's life and claiming one's rights",
    "example": "The workshop was designed to make women feel empowered in the workplace.",
    "pos": "adjective",
    "source_lang": "en",
    "target_lang": "vi",
    "popular_score": 85,
    "difficulty": 6,
    "collocations": ["feel empowered", "empowered to act"],
    "synonyms": ["authorized", "confident"],
    "topics": ["emotions", "work", "psychology"],
    "skills": ["writing", "reading"]
  },
  {
    "term": "gratified",
    "ipa": "/ˈɡrætɪfaɪd/",
    "target_translation": "hài lòng / mãn nguyện",
    "source_translation": "feeling pleasure or satisfaction, especially because of an achievement or receiving something desired",
    "example": "I was gratified to see that my hard work had finally paid off.",
    "pos": "adjective",
    "source_lang": "en",
    "target_lang": "vi",
    "popular_score": 79,
    "difficulty": 7,
    "collocations": ["deeply gratified", "gratified to hear"],
    "synonyms": ["satisfied", "pleased"],
    "topics": ["emotions", "success"],
    "skills": ["reading", "writing"]
  },
  {
    "term": "buoyant",
    "ipa": "/ˈbɔɪənt/",
    "target_translation": "vui vẻ / sôi nổi / lạc quan",
    "source_translation": "cheerful and optimistic",
    "example": "He was in a buoyant mood after hearing the good news.",
    "pos": "adjective",
    "source_lang": "en",
    "target_lang": "vi",
    "popular_score": 74,
    "difficulty": 8,
    "collocations": ["buoyant mood", "buoyant personality"],
    "synonyms": ["lighthearted", "carefree"],
    "topics": ["emotions", "happiness"],
    "skills": ["reading", "writing"]
  },
  {
    "term": "a sense of accomplishment",
    "ipa": "/ə sens əv əˈkɑːmplɪʃmənt/",
    "target_translation": "cảm giác thành tựu",
    "source_translation": "a feeling of satisfaction when you have done something difficult or important",
    "example": "Finishing the marathon gave her a huge sense of accomplishment.",
    "pos": "noun phrase",
    "source_lang": "en",
    "target_lang": "vi",
    "popular_score": 92,
    "difficulty": 5,
    "collocations": ["great sense of accomplishment"],
    "synonyms": ["sense of achievement"],
    "topics": ["emotions", "success"],
    "skills": ["speaking", "writing"]
  },
  {
    "term": "serene",
    "ipa": "/səˈriːn/",
    "target_translation": "thanh thản / bình yên",
    "source_translation": "calm, peaceful, and untroubled; tranquil",
    "example": "She looked serene as she meditated by the lake.",
    "pos": "adjective",
    "source_lang": "en",
    "target_lang": "vi",
    "popular_score": 83,
    "difficulty": 6,
    "collocations": ["serene expression", "perfectly serene"],
    "synonyms": ["calm", "tranquil"],
    "topics": ["emotions", "health"],
    "skills": ["reading", "writing"]
  },
  {
    "term": "enthusiastic",
    "ipa": "/ɪnˌθuːziˈæstɪk/",
    "target_translation": "hăng hái / nhiệt huyết",
    "source_translation": "having or showing intense and eager enjoyment, interest, or approval",
    "example": "The audience gave the performers an enthusiastic standing ovation.",
    "pos": "adjective",
    "source_lang": "en",
    "target_lang": "vi",
    "popular_score": 95,
    "difficulty": 4,
    "collocations": ["enthusiastic about", "enthusiastic support"],
    "synonyms": ["eager", "passionate"],
    "topics": ["emotions", "personality"],
    "skills": ["speaking", "listening"]
  },
  {
    "term": "walk on air",
    "ipa": "/wɔːk ɒn er/",
    "target_translation": "vô cùng hạnh phúc / sướng rơn",
    "source_translation": "to feel extremely happy and excited, as if one is floating",
    "example": "After he proposed and she said yes, he was walking on air for days.",
    "pos": "idiom",
    "source_lang": "en",
    "target_lang": "vi",
    "popular_score": 86,
    "difficulty": 5,
    "collocations": ["feel like walking on air"],
    "synonyms": ["over the moon", "elated"],
    "topics": ["emotions", "happiness"],
    "skills": ["speaking", "listening"]
  },
  {
    "term": "apathetic",
    "ipa": "/ˌæpəˈθetɪk/",
    "target_translation": "thờ ơ / vô cảm",
    "source_translation": "showing or feeling no interest, enthusiasm, or concern",
    "example": "Young people are often accused of being apathetic about local politics.",
    "pos": "adjective",
    "source_lang": "en",
    "target_lang": "vi",
    "popular_score": 78,
    "difficulty": 7,
    "collocations": ["become apathetic", "apathetic attitude"],
    "synonyms": ["indifferent", "uninterested"],
    "topics": ["emotions", "complexity"],
    "skills": ["reading", "writing"]
  },
  {
    "term": "drained",
    "ipa": "/dreɪnd/",
    "target_translation": "kiệt quệ / hết sạch năng lượng",
    "source_translation": "depleted of vitality or strength; extremely tired",
    "example": "I felt emotionally drained after the long and difficult conversation with my boss.",
    "pos": "adjective",
    "source_lang": "en",
    "target_lang": "vi",
    "popular_score": 92,
    "difficulty": 4,
    "collocations": ["completely drained", "emotionally drained"],
    "synonyms": ["exhausted", "spent"],
    "topics": ["emotions", "health"],
    "skills": ["speaking", "listening"]
  },
  {
    "term": "listless",
    "ipa": "/ˈlɪstləs/",
    "target_translation": "lờ đờ / vô hồn / thiếu sức sống",
    "source_translation": "lacking energy or enthusiasm to do anything",
    "example": "The illness left her feeling listless and unable to concentrate on her studies.",
    "pos": "adjective",
    "source_lang": "en",
    "target_lang": "vi",
    "popular_score": 74,
    "difficulty": 8,
    "collocations": ["feel listless", "listless performance"],
    "synonyms": ["lethargic", "enervated"],
    "topics": ["emotions", "health"],
    "skills": ["reading", "writing"]
  },
  {
    "term": "fed up",
    "ipa": "/fed ʌp/",
    "target_translation": "chán ngấy / hết chịu nổi",
    "source_translation": "annoyed or bored with something that you have been experiencing for too long",
    "example": "I'm fed up with this constant rain; I need some sunshine!",
    "pos": "adjective phrase",
    "source_lang": "en",
    "target_lang": "vi",
    "popular_score": 96,
    "difficulty": 3,
    "collocations": ["fed up with", "get fed up"],
    "synonyms": ["sick and tired"],
    "topics": ["emotions", "negative_feelings"],
    "skills": ["speaking", "listening"]
  },
  {
    "term": "nonchalant",
    "ipa": "/ˌnɑːnʃəˈlɑːnt/",
    "target_translation": "hờ hững / vô tâm / bình thản (đến mức lạnh lùng)",
    "source_translation": "feeling or appearing casually calm and relaxed; not displaying anxiety, interest, or enthusiasm",
    "example": "He gave a nonchalant shrug when I asked him if he was worried about the exam.",
    "pos": "adjective",
    "source_lang": "en",
    "target_lang": "vi",
    "popular_score": 81,
    "difficulty": 7,
    "collocations": ["nonchalant attitude", "remarkably nonchalant"],
    "synonyms": ["composed", "indifferent"],
    "topics": ["emotions", "personality"],
    "skills": ["reading", "writing"]
  },
  {
    "term": "bored to tears",
    "ipa": "/bɔːrd tə tɪrz/",
    "target_translation": "buồn chán đến phát khóc",
    "source_translation": "extremely bored",
    "example": "To be honest, I was bored to tears by that three-hour documentary.",
    "pos": "idiom",
    "source_lang": "en",
    "target_lang": "vi",
    "popular_score": 87,
    "difficulty": 4,
    "collocations": ["be bored to tears"],
    "synonyms": ["bored stiff", "bored out of one's mind"],
    "topics": ["emotions", "negative_feelings"],
    "skills": ["speaking", "listening"]
  },
  {
    "term": "jaded",
    "ipa": "/ˈdʒeɪdɪd/",
    "target_translation": "chán chường / mệt mỏi (vì đã trải qua quá nhiều)",
    "source_translation": "tired, bored, or lacking enthusiasm, typically after having had too much of something",
    "example": "After ten years in the industry, he had become a bit jaded about the whole process.",
    "pos": "adjective",
    "source_lang": "en",
    "target_lang": "vi",
    "popular_score": 79,
    "difficulty": 7,
    "collocations": ["feel jaded", "jaded view of the world"],
    "synonyms": ["satiated", "weary"],
    "topics": ["emotions", "experience"],
    "skills": ["reading", "writing"]
  },
  {
    "term": "not have the heart to",
    "ipa": "/nɒt hæv ðə hɑːrt tuː/",
    "target_translation": "không nỡ (làm gì đó)",
    "source_translation": "to feel too sorry for someone to do something that will upset them",
    "example": "I didn't have the heart to tell him that his singing was terrible.",
    "pos": "idiom",
    "source_lang": "en",
    "target_lang": "vi",
    "popular_score": 90,
    "difficulty": 5,
    "collocations": [],
    "synonyms": [],
    "topics": ["emotions", "empathy"],
    "skills": ["speaking", "listening"]
  },
  {
    "term": "complacent",
    "ipa": "/kəmˈpleɪsnt/",
    "target_translation": "tự mãn / chủ quan",
    "source_translation": "showing smug or uncritical satisfaction with oneself or one's achievements",
    "example": "We cannot afford to become complacent about our success; our competitors are catching up.",
    "pos": "adjective",
    "source_lang": "en",
    "target_lang": "vi",
    "popular_score": 82,
    "difficulty": 8,
    "collocations": ["grow complacent", "complacent attitude"],
    "synonyms": ["self-satisfied", "smug"],
    "topics": ["emotions", "personality"],
    "skills": ["reading", "writing"]
  },
  {
    "term": "lethargic",
    "ipa": "/ləˈθɑːrdʒɪk/",
    "target_translation": "hôn trầm / lờ đờ / mệt mỏi",
    "source_translation": "affected by lethargy; sluggish and apathetic",
    "example": "The hot weather makes me feel very lethargic and unmotivated.",
    "pos": "adjective",
    "source_lang": "en",
    "target_lang": "vi",
    "popular_score": 85,
    "difficulty": 6,
    "collocations": ["feel lethargic", "lethargic reaction"],
    "synonyms": ["sluggish", "lifeless"],
    "topics": ["emotions", "health"],
    "skills": ["reading", "listening"]
  },
  {
    "term": "compassionate",
    "ipa": "/kəmˈpæʃənət/",
    "target_translation": "lòng trắc ẩn / nhân ái",
    "source_translation": "feeling or showing sympathy and concern for others who are suffering",
    "example": "He is a compassionate person who spends his weekends volunteering at the shelter.",
    "pos": "adjective",
    "source_lang": "en",
    "target_lang": "vi",
    "popular_score": 93,
    "difficulty": 5,
    "collocations": ["compassionate leave", "compassionate care"],
    "synonyms": ["sympathetic", "kindhearted"],
    "topics": ["emotions", "social_bonds"],
    "skills": ["speaking", "writing"]
  },
  {
    "term": "affectionate",
    "ipa": "/əˈfekʃənət/",
    "target_translation": "trìu mến / âu yếm",
    "source_translation": "readily feeling or showing fondness or tenderness",
    "example": "She is very affectionate with her children, always giving them hugs.",
    "pos": "adjective",
    "source_lang": "en",
    "target_lang": "vi",
    "popular_score": 89,
    "difficulty": 6,
    "collocations": ["affectionate gesture", "affectionate nickname"],
    "synonyms": ["loving", "fond"],
    "topics": ["emotions", "family"],
    "skills": ["speaking", "reading"]
  },
  {
    "term": "a soft spot for",
    "ipa": "/ə sɔːft spɑːt fɔːr/",
    "target_translation": "có lòng thương cảm / sự ưu ái đặc biệt cho ai đó",
    "source_translation": "to feel a lot of affection for a particular person or thing",
    "example": "I've always had a soft spot for my youngest nephew.",
    "pos": "idiom",
    "source_lang": "en",
    "target_lang": "vi",
    "popular_score": 87,
    "difficulty": 4,
    "collocations": ["have a soft spot for"],
    "synonyms": ["fondness"],
    "topics": ["emotions", "social_life"],
    "skills": ["speaking", "listening"]
  },
  {
    "term": "heart-to-heart",
    "ipa": "/ˌhɑːrt tə ˈhɑːrt/",
    "target_translation": "chân tình / tâm sự mỏng",
    "source_translation": "a serious and honest conversation between two people about their feelings",
    "example": "We had a long heart-to-heart talk and finally cleared up the misunderstanding.",
    "pos": "noun/adjective",
    "source_lang": "en",
    "target_lang": "vi",
    "popular_score": 91,
    "difficulty": 3,
    "collocations": ["have a heart-to-heart", "heart-to-heart conversation"],
    "synonyms": [],
    "topics": ["communication", "emotions"],
    "skills": ["speaking", "listening"]
  },
  {
    "term": "smitten",
    "ipa": "/ˈsmɪtn/",
    "target_translation": "say mê / bị hớp hồn",
    "source_translation": "strongly attracted to someone or something",
    "example": "He was completely smitten with her from the moment they met.",
    "pos": "adjective",
    "source_lang": "en",
    "target_lang": "vi",
    "popular_score": 78,
    "difficulty": 6,
    "collocations": ["smitten with", "totally smitten"],
    "synonyms": ["infatuated", "enchanted"],
    "topics": ["emotions", "romance"],
    "skills": ["reading", "speaking"]
  },
  {
    "term": "empathy",
    "ipa": "/ˈempəθi/",
    "target_translation": "sự thấu cảm",
    "source_translation": "the ability to understand and share the feelings of another",
    "example": "Teachers need to have a lot of empathy for their students' struggles.",
    "pos": "noun",
    "source_lang": "en",
    "target_lang": "vi",
    "popular_score": 95,
    "difficulty": 5,
    "collocations": ["feel empathy for", "lack of empathy"],
    "synonyms": ["understanding"],
    "topics": ["emotions", "psychology"],
    "skills": ["reading", "writing"]
  },
  {
    "term": "alienated",
    "ipa": "/ˈeɪliəneɪtɪd/",
    "target_translation": "bị xa lánh / bị cô lập",
    "source_translation": "feeling that you do not belong in a particular group or place",
    "example": "The new student felt alienated because he didn't speak the local language.",
    "pos": "adjective",
    "source_lang": "en",
    "target_lang": "vi",
    "popular_score": 82,
    "difficulty": 7,
    "collocations": ["feel alienated from"],
    "synonyms": ["estranged", "isolated"],
    "topics": ["emotions", "social_life"],
    "skills": ["reading", "writing"]
  },
  {
    "term": "infatuated",
    "ipa": "/ɪnˈfætʃueɪtɪd/",
    "target_translation": "mê đắm / cuồng nhiệt (nhất thời)",
    "source_translation": "having an intense but short-lived passion or admiration for someone",
    "example": "She was infatuated with the pop star and had posters of him all over her room.",
    "pos": "adjective",
    "source_lang": "en",
    "target_lang": "vi",
    "popular_score": 75,
    "difficulty": 8,
    "collocations": ["infatuated with"],
    "synonyms": ["obsessed", "smitten"],
    "topics": ["emotions", "romance"],
    "skills": ["reading", "writing"]
  },
  {
    "term": "appreciation",
    "ipa": "/əˌpriːʃiˈeɪʃn/",
    "target_translation": "sự trân trọng / cảm kích",
    "source_translation": "the recognition and enjoyment of the good qualities of someone or something",
    "example": "I want to express my deep appreciation for all your help during the move.",
    "pos": "noun",
    "source_lang": "en",
    "target_lang": "vi",
    "popular_score": 94,
    "difficulty": 4,
    "collocations": ["show appreciation", "token of appreciation"],
    "synonyms": ["gratitude", "thankfulness"],
    "topics": ["emotions", "social_life"],
    "skills": ["speaking", "writing"]
  },
  {
    "term": "longing",
    "ipa": "/ˈlɔːŋɪŋ/",
    "target_translation": "khao khát / mong mỏi",
    "source_translation": "a strong wish for something or someone that is difficult or impossible to get",
    "example": "He felt a deep longing to return to his home country.",
    "pos": "noun/adjective",
    "source_lang": "en",
    "target_lang": "vi",
    "popular_score": 86,
    "difficulty": 6,
    "collocations": ["longing for", "a sense of longing"],
    "synonyms": ["yearning", "craving"],
    "topics": ["emotions", "desire"],
    "skills": ["reading", "writing"]
  },
  {
    "term": "vibe",
    "ipa": "/vaɪb/",
    "target_translation": "cảm giác / năng lượng (của một người/nơi)",
    "source_translation": "a person's emotional state or the atmosphere of a place as communicated to others",
    "example": "I didn't like the vibe of that coffee shop; it felt very unfriendly.",
    "pos": "noun (informal)",
    "source_lang": "en",
    "target_lang": "vi",
    "popular_score": 98,
    "difficulty": 3,
    "collocations": ["good vibes", "get a bad vibe"],
    "synonyms": ["atmosphere", "aura"],
    "topics": ["emotions", "social_life"],
    "skills": ["speaking", "listening"]
  },
  {
    "term": "bitter",
    "ipa": "/ˈbɪtər/",
    "target_translation": "cay đắng / hằn học",
    "source_translation": "feeling angry, jealous, and resentful because you think you have been treated unfairly",
    "example": "She was still bitter about the way her marriage had ended.",
    "pos": "adjective",
    "source_lang": "en",
    "target_lang": "vi",
    "popular_score": 90,
    "difficulty": 4,
    "collocations": ["bitter disappointment", "bitter pill to swallow"],
    "synonyms": ["resentful", "sour"],
    "topics": ["emotions", "negative_feelings"],
    "skills": ["speaking", "reading"]
  },
  {
    "term": "devotion",
    "ipa": "/dɪˈvəʊʃn/",
    "target_translation": "sự tận tâm / lòng trung thành",
    "source_translation": "love, loyalty, or enthusiasm for a person, activity, or cause",
    "example": "His devotion to his work is truly admirable.",
    "pos": "noun",
    "source_lang": "en",
    "target_lang": "vi",
    "popular_score": 85,
    "difficulty": 7,
    "collocations": ["total devotion", "devotion to family"],
    "synonyms": ["loyalty", "dedication"],
    "topics": ["emotions", "personality"],
    "skills": ["reading", "writing"]
  },
  {
    "term": "remorse",
    "ipa": "/rɪˈmɔːrs/",
    "target_translation": "sự hối hận / cắn rứt",
    "source_translation": "deep regret or guilt for a wrong committed",
    "example": "The prisoner showed no remorse for the crimes he had committed.",
    "pos": "noun",
    "source_lang": "en",
    "target_lang": "vi",
    "popular_score": 83,
    "difficulty": 7,
    "collocations": ["feel remorse", "full of remorse"],
    "synonyms": ["regret", "guilt"],
    "topics": ["emotions", "psychology"],
    "skills": ["reading", "writing"]
  },
  {
    "term": "shaken",
    "ipa": "/ˈʃeɪkən/",
    "target_translation": "bị sốc / rúng động",
    "source_translation": "emotionally or physically disturbed or upset",
    "example": "She was visibly shaken after the car accident, even though she wasn't hurt.",
    "pos": "adjective",
    "source_lang": "en",
    "target_lang": "vi",
    "popular_score": 88,
    "difficulty": 5,
    "collocations": ["deeply shaken", "shaken by the news"],
    "synonyms": ["disturbed", "unsettled"],
    "topics": ["emotions", "fear"],
    "skills": ["speaking", "listening"]
  },
  {
    "term": "tender",
    "ipa": "/ˈtendər/",
    "target_translation": "dịu dàng / âu yếm",
    "source_translation": "showing gentleness and concern or sympathy",
    "example": "He gave her a tender kiss on the forehead before leaving.",
    "pos": "adjective",
    "source_lang": "en",
    "target_lang": "vi",
    "popular_score": 87,
    "difficulty": 5,
    "collocations": ["tender moment", "tender care"],
    "synonyms": ["gentle", "soft"],
    "topics": ["emotions", "social_bonds"],
    "skills": ["speaking", "reading"]
  },
  {
    "term": "glow with happiness",
    "ipa": "/ɡləʊ wɪð ˈhæpinəs/",
    "target_translation": "rạng ngời hạnh phúc",
    "source_translation": "to look very happy and healthy",
    "example": "The bride was absolutely glowing with happiness as she walked down the aisle.",
    "pos": "verb phrase",
    "source_lang": "en",
    "target_lang": "vi",
    "popular_score": 84,
    "difficulty": 4,
    "collocations": [],
    "synonyms": [],
    "topics": ["emotions", "happiness"],
    "skills": ["speaking", "listening"]
  },
  {
    "term": "comfort",
    "ipa": "/ˈkʌmfərt/",
    "target_translation": "sự an ủi / xoa dịu",
    "source_translation": "a state of physical ease and freedom from pain or constraint; the easing of a person's feelings",
    "example": "The kind words from her friends brought her much comfort after her loss.",
    "pos": "noun/verb",
    "source_lang": "en",
    "target_lang": "vi",
    "popular_score": 96,
    "difficulty": 3,
    "collocations": ["seek comfort", "offer comfort"],
    "synonyms": ["consolation", "solace"],
    "topics": ["emotions", "support"],
    "skills": ["speaking", "listening"]
  }
]

